CHANGES.txt
MANIFEST.in
README.md
package.json
requirements-pysal.txt
requirements.txt
setup.py
GeobricksRasterCorrelation.egg-info/PKG-INFO
GeobricksRasterCorrelation.egg-info/SOURCES.txt
GeobricksRasterCorrelation.egg-info/dependency_links.txt
GeobricksRasterCorrelation.egg-info/entry_points.txt
GeobricksRasterCorrelation.egg-info/pbr.json
GeobricksRasterCorrelation.egg-info/top_level.txt
geobricks_raster_correlation/__init__.py
geobricks_raster_correlation/__init__.pyc
geobricks_raster_correlation/cli/__init__.py
geobricks_raster_correlation/cli/cli.py
geobricks_raster_correlation/cli/cli_argh.py
geobricks_raster_correlation/config/__init__.py
geobricks_raster_correlation/config/__init__.pyc
geobricks_raster_correlation/config/config.py
geobricks_raster_correlation/config/config.pyc
geobricks_raster_correlation/core/__init__.py
geobricks_raster_correlation/core/__init__.pyc
geobricks_raster_correlation/core/colors.py
geobricks_raster_correlation/core/colors.pyc
geobricks_raster_correlation/core/raster_correlation_core.py
geobricks_raster_correlation/core/raster_correlation_core.pyc
geobricks_raster_correlation/core/raster_correlation_core_gdal.py
geobricks_raster_correlation/rest/__init__.py
geobricks_raster_correlation/rest/__init__.pyc
geobricks_raster_correlation/rest/raster_correlation_main.py
geobricks_raster_correlation/rest/raster_correlation_rest.py
geobricks_raster_correlation/rest/raster_correlation_rest.pyc