Metadata-Version: 1.0
Name: GeobricksRasterCorrelation
Version: 0.1.13
Summary: Geobricks library to correlate two raster and create statistics and scatter charts.
Home-page: http://pypi.python.org/pypi/GeobricksRasterCorrelation/
Author: Simone Murzilli; Guido Barbaglia
Author-email: geobrickspy@gmail.com
License: LICENSE.txt
Keywords: geobricks,processing,raster,gis,gdal,correlation,raster correlation,highcharts
Platform: UNKNOWN
